Metadata-Version: 1.1
Name: python-vote-full
Version: 1.0
Summary: Python based election methods, includes python-vote-core and python-graph-core.
Home-page: https://github.com/bradbeattie/python-vote-core
Author: Brad Beattie
Author-email: bradbeattie@gmail com
License: GPLv3
Keywords: library election
Platform: UNKNOWN
Classifier: Development Status :: 5 - Production/Stable
Classifier: License :: OSI Approved :: GNU General Public License (GPL)
Classifier: Programming Language :: Python
Classifier: Programming Language :: Python :: 2.7
Classifier: Topic :: Scientific/Engineering :: Mathematics
